cw_tiler/__init__.py
cw_tiler/main.py
cw_tiler/utils.py
cw_tiler/vector_utils.py
cw_tiler-0.2.0.dist-info/AUTHORS.txt
cw_tiler-0.2.0.dist-info/LICENSE.txt
cw_tiler-0.2.0.dist-info/METADATA
cw_tiler-0.2.0.dist-info/WHEEL
cw_tiler-0.2.0.dist-info/top_level.txt
cw_tiler-0.2.0.dist-info/RECORD
