Metadata-Version: 2.1
Name: cw-tiler
Version: 0.2.0
Summary: Get UTM tiles for SpaceNet Dataset or arbitrary GeoTiffs
Home-page: https://github.com/CosmiQ/cw-tiler
Author: David Lindenbaum and Nick Weir
Author-email: dlindenbaum@iqt.org, nweir@iqt.org
License: BSD
Keywords: raster aws tiler gdal rasterio spacenet machinelearning
Platform: UNKNOWN
Classifier: Intended Audience :: Information Technology
Classifier: Intended Audience :: Science/Research
Classifier: License :: OSI Approved :: BSD License
Classifier: Programming Language :: Python :: 3.6
Classifier: Programming Language :: Python :: 2.7
Classifier: Topic :: Scientific/Engineering :: GIS
Requires-Dist: rio-tiler
Requires-Dist: shapely
Requires-Dist: geopandas
Provides-Extra: test
Requires-Dist: mock ; extra == 'test'
Requires-Dist: pytest ; extra == 'test'
Requires-Dist: pytest-cov ; extra == 'test'
Requires-Dist: codecov ; extra == 'test'
